LICENSE.txt
README.md
pyproject.toml
setup.cfg
setup.py
photofitt/__init__.py
photofitt/version.py
photofitt.egg-info/PKG-INFO
photofitt.egg-info/SOURCES.txt
photofitt.egg-info/dependency_links.txt
photofitt.egg-info/requires.txt
photofitt.egg-info/top_level.txt
photofitt/analysis/__init__.py
photofitt/analysis/fov_activity.py
photofitt/analysis/mitosis_counting.py
photofitt/analysis/unsynchro.py
photofitt/display/__init__.py
photofitt/display/mosaics.py
photofitt/display/plots.py
photofitt/utils/__init__.py
photofitt/utils/data.py
photofitt/utils/morphology.py
photofitt/utils/normalisation.py
photofitt/utils/utils.py