Metadata-Version: 2.1
Name: photofitt
Version: 1.0.1
Summary: PhotoFiTT: Phototoxicity Fitness Time Trial. Python package for assessing phototoxicity in live-cell microscopy experiments.
Home-page: https://github.com/HenriquesLab/photofitt
Download-URL: https://github.com/HenriquesLab/photofitt/archive/refs/tags/v1.0.0.tar.gz
Author: M. del Rosario, E. Gómez-de-Mariscal, L. Morgado, R. Portela, G. Jacquemet, P.M. Pereira, R. Henriques
Author-email: mrosario@igc.gulbenkian.pt, egomez@igc.gulbenkian.pt, rjhenriques@igc.gulbenkian.pt
License: MIT
Keywords: phototoxicity,cell arrest,bioimage analysis,cell mitosis,live-cell microscopy
Classifier: Development Status :: 3 - Alpha
Classifier: Intended Audience :: Science/Research
Classifier: Intended Audience :: Education
Classifier: Topic :: Scientific/Engineering
Classifier: License :: OSI Approved :: MIT License
Classifier: Programming Language :: Python :: 3
Requires-Python: >=3.10
License-File: LICENSE.txt
Requires-Dist: dask
Requires-Dist: czifile==2019.7.2
Requires-Dist: jupyter
Requires-Dist: imageio==2.13.3
Requires-Dist: matplotlib==3.5.1
Requires-Dist: nd2==0.1.6
Requires-Dist: numpy==1.22.4
Requires-Dist: opencv-python==4.7.0.72
Requires-Dist: pyyaml==6.0
Requires-Dist: pandas==1.5.2
Requires-Dist: pillow==8.4.0
Requires-Dist: scipy==1.7.3
Requires-Dist: scikit-image==0.19.1
Requires-Dist: scikit-learn==1.2.1
Requires-Dist: seaborn==0.12.2
Requires-Dist: tifffile==2021.10.12
Requires-Dist: toolz==0.11.2
Requires-Dist: statsmodels
